Metadata-Version: 1.0
Name: straintables
Version: 1.4
Summary: Build & Compare dissimilarity matrices for genomic regions
Home-page: https://www.github.com/Gab0/straintables
Author: Gabriel Araujo
Author-email: gabriel_scf@hotmail.com
License: UNKNOWN
Platform: any
